driftmonitor/__init__.py
driftmonitor/alert_manager.py
driftmonitor/drift_detector.py
driftmonitor/drift_monitor_wrapper.py
driftmonitor/model_monitor.py
driftmonitor/version_manager.py
driftmonitor/utils/__init__.py
driftmonitor/utils/data_utils.py
tests/__init__.py
tests/test_alert_manager.py
tests/test_drift_detector.py
tests/test_drift_monitor_wrapper.py
tests/test_model_monitor.py
tests/test_version_manager.py
driftdetector-0.1.0.dist-info/LICENSE
driftdetector-0.1.0.dist-info/METADATA
driftdetector-0.1.0.dist-info/WHEEL
driftdetector-0.1.0.dist-info/entry_points.txt
driftdetector-0.1.0.dist-info/top_level.txt
driftdetector-0.1.0.dist-info/RECORD
