Metadata-Version: 2.2
Name: driftdetector
Version: 0.1.0
Summary: A lightweight Python library for monitoring data and concept drift in machine learning models.
Home-page: https://github.com/kiplangatkorir/driftmonitor
Author: Kiplangat Korir
Author-email: korirkiplangat22@gmail.com
Classifier: Programming Language :: Python :: 3
Classifier: License :: OSI Approved :: MIT License
Classifier: Operating System :: OS Independent
Requires-Python: >=3.6
License-File: LICENSE
Requires-Dist: numpy
Requires-Dist: scikit-learn
Requires-Dist: pandas
Requires-Dist: scipy
Requires-Dist: matplotlib
Dynamic: author
Dynamic: author-email
Dynamic: classifier
Dynamic: description
Dynamic: description-content-type
Dynamic: home-page
Dynamic: requires-dist
Dynamic: requires-python
Dynamic: summary
